ad_notify/__init__.py
ad_notify/ad_notify.py
ad_notify-0.1.3.dist-info/METADATA
ad_notify-0.1.3.dist-info/WHEEL
ad_notify-0.1.3.dist-info/top_level.txt
ad_notify-0.1.3.dist-info/RECORD
