Metadata-Version: 2.1
Name: ad-notify
Version: 0.1.3
Summary: notify library
Home-page: https://github.com/ad-developer-tk
Author: Toshiaki Kosuga
Author-email: toshiaki.kosuga@gmail.com
Maintainer: Toshiaki Kosuga
Maintainer-email: toshiaki.kosuga@gmail.com
License: BSD License
Download-URL: https://github.com/ad-developer-tk/notify
Platform: UNKNOWN
Classifier: Intended Audience :: Science/Research
Classifier: License :: OSI Approved :: BSD License
Classifier: Programming Language :: Python :: 3.6
Requires-Python: >=3.6
Provides-Extra: tutorial
